[
  {
    "count": 4,
    "name": "National Park Passport Stamp",
    "category": [
      "National Park Passport Stamp"
    ],
    "progression": true
  },
  {
    "count": 1,
    "name": "Wiper Blades",
    "category": [
      "Vehicle Unlock"
    ],
    "useful": true
  },
  {
    "count": 1,
    "name": "Headlights",
    "category": [
      "Vehicle Unlock"
    ],
    "useful": true
  },
  {
    "count": 1,
    "name": "Unlock Fast Travel - Burlington",
    "category": [
      "Fast Travel Unlock",
      "DLC - Colorado",
      "Colorado"
    ],
    "progression": true
  },
  {
    "count": 1,
    "name": "Unlock Fast Travel - Alamosa",
    "category": [
      "Fast Travel Unlock",
      "DLC - Colorado",
      "Colorado"
    ],
    "progression": true
  },
  {
    "count": 1,
    "name": "Unlock Fast Travel - Steamboat Springs",
    "category": [
      "Fast Travel Unlock",
      "DLC - Colorado",
      "Colorado"
    ],
    "progression": true
  },
  {
    "count": 1,
    "name": "Unlock Fast Travel - Colorado Springs",
    "category": [
      "Fast Travel Unlock",
      "DLC - Colorado",
      "Colorado"
    ],
    "progression": true
  },
  {
    "count": 1,
    "name": "Unlock Fast Travel - Denver",
    "category": [
      "Fast Travel Unlock",
      "DLC - Colorado",
      "Colorado"
    ],
    "progression": true
  },
  {
    "count": 1,
    "name": "Unlock Fast Travel - Fort Collins",
    "category": [
      "Fast Travel Unlock",
      "DLC - Colorado",
      "Colorado"
    ],
    "progression": true
  },
  {
    "count": 1,
    "name": "Unlock Fast Travel - Pueblo",
    "category": [
      "Fast Travel Unlock",
      "DLC - Colorado",
      "Colorado"
    ],
    "progression": true
  },
  {
    "count": 1,
    "name": "Unlock Fast Travel - Durango",
    "category": [
      "Fast Travel Unlock",
      "DLC - Colorado",
      "Colorado"
    ],
    "progression": true
  },
  {
    "count": 1,
    "name": "Unlock Fast Travel - Grand Junction",
    "category": [
      "Fast Travel Unlock",
      "DLC - Colorado",
      "Colorado"
    ],
    "progression": true
  },
  {
    "count": 1,
    "name": "Unlock Fast Travel - Montrose",
    "category": [
      "Fast Travel Unlock",
      "DLC - Colorado",
      "Colorado"
    ],
    "progression": true
  },
  {
    "count": 1,
    "name": "Unlock Fast Travel - Provo",
    "category": [
      "Fast Travel Unlock",
      "DLC - Utah",
      "Utah"
    ],
    "progression": true
  },
  {
    "count": 1,
    "name": "Unlock Fast Travel - Vernal",
    "category": [
      "Fast Travel Unlock",
      "DLC - Utah",
      "Utah"
    ],
    "progression": true
  },
  {
    "count": 1,
    "name": "Unlock Fast Travel - Price",
    "category": [
      "Fast Travel Unlock",
      "DLC - Utah",
      "Utah"
    ],
    "progression": true
  },
  {
    "count": 1,
    "name": "Unlock Fast Travel - Salina",
    "category": [
      "Fast Travel Unlock",
      "DLC - Utah",
      "Utah"
    ],
    "progression": true
  },
  {
    "count": 1,
    "name": "Unlock Fast Travel - Salt Lake City",
    "category": [
      "Fast Travel Unlock",
      "DLC - Utah",
      "Utah"
    ],
    "progression": true
  },
  {
    "count": 1,
    "name": "Unlock Fast Travel - Ogden",
    "category": [
      "Fast Travel Unlock",
      "DLC - Utah",
      "Utah"
    ],
    "progression": true
  },
  {
    "count": 1,
    "name": "Unlock Fast Travel - Logan",
    "category": [
      "Fast Travel Unlock",
      "DLC - Utah",
      "Utah"
    ],
    "progression": true
  },
  {
    "count": 1,
    "name": "Unlock Fast Travel - Moab",
    "category": [
      "Fast Travel Unlock",
      "DLC - Utah",
      "Utah"
    ],
    "progression": true
  },
  {
    "count": 1,
    "name": "Unlock Fast Travel - Cedar City",
    "category": [
      "Fast Travel Unlock",
      "DLC - Utah",
      "Utah"
    ],
    "progression": true
  },
  {
    "count": 1,
    "name": "Unlock Fast Travel - St. George",
    "category": [
      "Fast Travel Unlock",
      "DLC - Utah",
      "Utah"
    ],
    "progression": true
  },
  {
    "count": 1,
    "name": "Unlock Northern Utah",
    "category": [
      "Region Unlock",
      "DLC - Utah",
      "Utah",
      "Start Region"
    ],
    "progression": true
  },
  {
    "count": 1,
    "name": "Unlock Central Utah",
    "category": [
      "Region Unlock",
      "DLC - Utah",
      "Utah",
      "Start Region"
    ],
    "progression": true
  },
  {
    "count": 1,
    "name": "Unlock St. George Area",
    "category": [
      "Region Unlock",
      "DLC - Utah",
      "Utah",
      "Start Region"
    ],
    "progression": true
  },
  {
    "count": 1,
    "name": "Unlock Southeast Utah",
    "category": [
      "Region Unlock",
      "DLC - Utah",
      "Utah",
      "Start Region"
    ],
    "progression": true
  },
  {
    "count": 1,
    "name": "Unlock Four Corners",
    "category": [
      "Region Unlock",
      "DLC - Colorado",
      "Colorado",
      "Utah"
    ],
    "progression": true
  },
  {
    "count": 1,
    "name": "Unlock Western Slope",
    "category": [
      "Region Unlock",
      "DLC - Colorado",
      "Colorado",
      "Start Region"
    ],
    "progression": true
  },
  {
    "count": 1,
    "name": "Unlock Colorado Rockies",
    "category": [
      "Region Unlock",
      "DLC - Colorado",
      "Colorado",
      "Start Region"
    ],
    "progression": true
  },
  {
    "count": 1,
    "name": "Unlock Front Range",
    "category": [
      "Region Unlock",
      "DLC - Colorado",
      "Colorado",
      "Start Region"
    ],
    "progression": true
  },
  {
    "count": 1,
    "name": "Unlock Colorado Plains",
    "category": [
      "Region Unlock",
      "DLC - Colorado",
      "Colorado",
      "Start Region"
    ],
    "progression": true
  }
]